{"water":{"type":"FeatureCollection","features":[]},"buildings":{"type":"FeatureCollection","features":[{"geometry":{"type":"Polygon","coordinates":[[[-2.2874704,53.45168168],[-2.28736018,53.45171067],[-2.28726181,53.45157828],[-2.28721312,53.45159117],[-2.28713919,53.45149167],[-2.28733529,53.45143999],[-2.28744022,53.45158111],[-2.28740294,53.45159101],[-2.2874704,53.45168168]]]},"type":"Feature","properties":{"kind":"building","area":887,"sort_rank":475,"landuse_kind":"park","scale_rank":5,"source":"openstreetmap.org","min_zoom":14.0,"id":359983702}},{"geometry":{"type":"Polygon","coordinates":[[[-2.28703966,53.45182382],[-2.28696842,53.45189908],[-2.28670135,53.45180948],[-2.28676711,53.45173999],[-2.28683798,53.45176379],[-2.28689018,53.45170848],[-2.28701441,53.4517501],[-2.28696752,53.45179969],[-2.28703966,53.45182382]]]},"type":"Feature","properties":{"kind":"building","name":"Beacon Centre","area":708,"sort_rank":475,"id":241948025,"source":"openstreetmap.org","min_zoom":14.0,"scale_rank":5}},{"geometry":{"type":"Point","coordinates":[-2.28684407,53.45180458]},"type":"Feature","properties":{"label_placement":true,"kind":"building","name":"Beacon Centre","area":708,"sort_rank":475,"scale_rank":5,"source":"openstreetmap.org","min_zoom":14.0,"id":241948025}}]},"places":{"type":"FeatureCollection","features":[]},"transit":{"type":"FeatureCollection","features":[]},"pois":{"type":"FeatureCollection","features":[{"geometry":{"type":"Point","coordinates":[-2.28662787,53.4505522]},"type":"Feature","properties":{"kind":"pitch","area":17968,"kind_detail":"soccer","source":"openstreetmap.org","min_zoom":16.0,"tier":6,"sport":"soccer","id":323153590}},{"geometry":{"type":"Point","coordinates":[-2.28675669,53.45196649]},"type":"Feature","properties":{"source":"openstreetmap.org","kind":"bus_stop","min_zoom":17.0,"name":"The Quadrant\/Greatstone Road","id":533835255}},{"geometry":{"type":"Point","coordinates":[-2.2901057,53.4516445]},"type":"Feature","properties":{"source":"openstreetmap.org","kind":"bus_stop","min_zoom":17.0,"name":"Kings Road\/Kings Terrace","id":533835265}},{"geometry":{"type":"Point","coordinates":[-2.29024574,53.45141121]},"type":"Feature","properties":{"source":"openstreetmap.org","kind":"bus_stop","min_zoom":17.0,"name":"Kings Road\/Kings Terrace","id":533835272}}]},"boundaries":{"type":"FeatureCollection","features":[{"geometry":{"type":"LineString","coordinates":[[-2.28649778,53.44880684],[-2.2862539,53.4490832],[-2.2861673,53.44918228],[-2.28613424,53.44918961],[-2.28564915,53.44915387],[-2.28563254,53.44914938],[-2.28544973,53.44905282],[-2.28515625,53.44902114]]},"type":"Feature","properties":{"kind":"locality","name":"Trafford - Manchester","sort_rank":252,"kind_detail":"8","name:right:ko":"\ub9e8\uccb4\uc2a4\ud130","id:right":-146656,"source":"openstreetmap.org","min_zoom":10.0,"id:left":-146675,"name:left":"Trafford","id":-146675,"osm_relation":true,"name:right":"Manchester"}}]},"roads":{"type":"FeatureCollection","features":[{"geometry":{"type":"LineString","coordinates":[[-2.28607388,53.45188967],[-2.28614763,53.45193439],[-2.28621716,53.45196506]]},"type":"Feature","properties":{"kind":"major_road","name":"Great Stone Rd.","sort_rank":377,"kind_detail":"tertiary","source":"openstreetmap.org","min_zoom":11.0,"oneway":"yes","landuse_kind":"residential","id":115563710}},{"geometry":{"type":"LineString","coordinates":[[-2.28621716,53.45196506],[-2.28623081,53.45197109],[-2.28633142,53.45198788]]},"type":"Feature","properties":{"kind":"major_road","name":"Great Stone Rd.","sort_rank":377,"kind_detail":"tertiary","source":"openstreetmap.org","min_zoom":11.0,"oneway":"yes","id":115563710}},{"geometry":{"type":"LineString","coordinates":[[-2.28804674,53.45207811],[-2.2887478,53.4518879],[-2.29026263,53.45146497],[-2.29064941,53.45135396]]},"type":"Feature","properties":{"kind":"major_road","name":"Kings Rd.","sort_rank":377,"landuse_kind":"residential","source":"openstreetmap.org","min_zoom":11.0,"kind_detail":"tertiary","id":112414478}},{"geometry":{"type":"LineString","coordinates":[[-2.28827302,53.44880684],[-2.28809679,53.44900017],[-2.28780448,53.44949219],[-2.28760065,53.45011827],[-2.28746124,53.45065018],[-2.28838291,53.4515182],[-2.2870781,53.45185618]]},"type":"Feature","properties":{"kind":"path","sort_rank":354,"landuse_kind":"park","is_bicycle_related":true,"source":"openstreetmap.org","min_zoom":13.0,"kind_detail":"cycleway","id":241948029}},{"geometry":{"type":"LineString","coordinates":[[-2.28552743,53.4491856],[-2.28558946,53.44912663]]},"type":"Feature","properties":{"source":"openstreetmap.org","kind":"path","kind_detail":"footway","sort_rank":354,"landuse_kind":"residential","min_zoom":14.0,"id":103043174}},{"geometry":{"type":"LineString","coordinates":[[-2.28558946,53.44912663],[-2.28561646,53.44910096],[-2.28622578,53.44914569]]},"type":"Feature","properties":{"source":"openstreetmap.org","kind":"path","sort_rank":354,"kind_detail":"footway","min_zoom":14.0,"id":103043174}},{"geometry":{"type":"LineString","coordinates":[[-2.29026263,53.45146497],[-2.29063849,53.45192909],[-2.29064941,53.45194387]]},"type":"Feature","properties":{"kind":"minor_road","name":"Kings Ter.","sort_rank":360,"landuse_kind":"residential","source":"openstreetmap.org","min_zoom":12.0,"kind_detail":"residential","id":4852831}},{"geometry":{"type":"LineString","coordinates":[[-2.29064941,53.45206542],[-2.29063031,53.45207811]]},"type":"Feature","properties":{"kind":"minor_road","name":"Kings Ln.","sort_rank":360,"landuse_kind":"residential","source":"openstreetmap.org","min_zoom":12.0,"kind_detail":"residential","id":112414466}},{"geometry":{"type":"LineString","coordinates":[[-2.28706413,53.45187169],[-2.2870781,53.45185618],[-2.28710982,53.45182098],[-2.28715006,53.45175871],[-2.28715006,53.45170442],[-2.28711781,53.4516613],[-2.28707218,53.45163568],[-2.28699456,53.45161979],[-2.28692476,53.451623]]},"type":"Feature","properties":{"source":"openstreetmap.org","kind":"minor_road","kind_detail":"service","sort_rank":358,"landuse_kind":"park","min_zoom":14.0,"id":241948028}},{"geometry":{"type":"LineString","coordinates":[[-2.28687824,53.45207811],[-2.28706413,53.45187169]]},"type":"Feature","properties":{"source":"openstreetmap.org","kind":"minor_road","sort_rank":358,"kind_detail":"service","min_zoom":14.0,"id":241948028}},{"geometry":{"type":"MultiLineString","coordinates":[[[-2.28638955,53.45197879],[-2.28646725,53.45196777],[-2.28659571,53.451969],[-2.28671249,53.45199628],[-2.28681157,53.4520563],[-2.28683564,53.45207811]],[[-2.28608056,53.45207811],[-2.28608062,53.45207807],[-2.28617404,53.45203057],[-2.28633142,53.45198788],[-2.28638955,53.45197879]]]},"type":"Feature","properties":{"source":"openstreetmap.org","kind":"major_road","name":"The Quadrant","sort_rank":377,"kind_detail":"tertiary","min_zoom":11.0,"id":4852811}},{"geometry":{"type":"LineString","coordinates":[[-2.28515625,53.44943827],[-2.28552743,53.4491856]]},"type":"Feature","properties":{"kind":"minor_road","name":"Rye Bank Rd.","sort_rank":360,"landuse_kind":"residential","source":"openstreetmap.org","min_zoom":12.0,"kind_detail":"residential","id":115563715}},{"geometry":{"type":"LineString","coordinates":[[-2.28889667,53.45207811],[-2.2887478,53.4518879]]},"type":"Feature","properties":{"kind":"minor_road","name":"Kings Grove","sort_rank":360,"landuse_kind":"residential","source":"openstreetmap.org","min_zoom":12.0,"kind_detail":"residential","id":4852830}},{"geometry":{"type":"LineString","coordinates":[[-2.28838291,53.4515182],[-2.29037142,53.4509649],[-2.29049476,53.450909],[-2.29055369,53.45084507],[-2.29064941,53.45064146]]},"type":"Feature","properties":{"source":"openstreetmap.org","kind":"path","kind_detail":"footway","sort_rank":354,"landuse_kind":"park","min_zoom":14.0,"id":241948023}},{"geometry":{"type":"LineString","coordinates":[[-2.28609951,53.45201292],[-2.2860967,53.45198071],[-2.28607388,53.45188967]]},"type":"Feature","properties":{"kind":"major_road","name":"Great Stone Rd.","sort_rank":377,"kind_detail":"tertiary","source":"openstreetmap.org","min_zoom":11.0,"oneway":"yes","landuse_kind":"residential","id":115563736}},{"geometry":{"type":"LineString","coordinates":[[-2.28608062,53.45207807],[-2.28610074,53.45202699],[-2.28609951,53.45201292]]},"type":"Feature","properties":{"kind":"major_road","name":"Great Stone Rd.","sort_rank":377,"kind_detail":"tertiary","source":"openstreetmap.org","min_zoom":11.0,"oneway":"yes","id":115563736}},{"geometry":{"type":"LineString","coordinates":[[-2.28515625,53.45110467],[-2.28538334,53.45131861],[-2.28607388,53.45188967]]},"type":"Feature","properties":{"kind":"major_road","name":"Great Stone Rd.","sort_rank":377,"landuse_kind":"residential","source":"openstreetmap.org","min_zoom":11.0,"kind_detail":"tertiary","id":4852773}},{"geometry":{"type":"LineString","coordinates":[[-2.28538334,53.45131861],[-2.28515625,53.45139663]]},"type":"Feature","properties":{"kind":"minor_road","name":"Woburn Rd.","sort_rank":360,"landuse_kind":"residential","source":"openstreetmap.org","min_zoom":12.0,"kind_detail":"residential","id":4887352}}]},"earth":{"type":"FeatureCollection","features":[{"geometry":{"type":"Polygon","coordinates":[[[-2.28515625,53.45207811],[-2.28515625,53.44880684],[-2.29064941,53.44880684],[-2.29064941,53.45207811],[-2.28515625,53.45207811]]]},"type":"Feature","properties":{"sort_rank":10,"source":"openstreetmapdata.com","kind":"earth","id":520855}}]},"landuse":{"type":"FeatureCollection","features":[{"geometry":{"type":"Polygon","coordinates":[[[-2.28713981,53.45207811],[-2.28707245,53.45199259],[-2.28711673,53.4519193],[-2.29048514,53.45104969],[-2.29064941,53.4509999],[-2.29064941,53.45207811],[-2.28713981,53.45207811]]]},"type":"Feature","properties":{"source":"openstreetmap.org","kind":"residential","tier":2,"area":1348410,"sort_rank":20,"min_zoom":10.0,"id":112917119}},{"geometry":{"type":"Polygon","coordinates":[[[-2.29064941,53.4509999],[-2.29048514,53.45104969],[-2.28711673,53.4519193],[-2.28682011,53.45165081],[-2.28515625,53.45014461],[-2.28515625,53.45007319],[-2.28578615,53.44956869],[-2.28614745,53.44922107],[-2.28622578,53.44914569],[-2.2862751,53.44909818],[-2.28652259,53.44880684],[-2.29064941,53.44880684],[-2.29064941,53.4509999]]]},"type":"Feature","properties":{"source":"openstreetmap.org","kind":"park","tier":2,"area":838587,"sort_rank":24,"min_zoom":11.0,"id":4852923}},{"geometry":{"type":"MultiPolygon","coordinates":[[[[-2.28515625,53.45207811],[-2.28515625,53.45014461],[-2.28682011,53.45165081],[-2.28639359,53.45189331],[-2.28599626,53.45205491],[-2.28596405,53.45207811],[-2.28515625,53.45207811]]],[[[-2.28515625,53.44902114],[-2.28544973,53.44905282],[-2.28563254,53.44914938],[-2.28564915,53.44915387],[-2.28613424,53.44918961],[-2.28614745,53.44922107],[-2.28578615,53.44956869],[-2.28515625,53.45007319],[-2.28515625,53.44902114]]]]},"type":"Feature","properties":{"kind":"residential","area":691853,"sort_rank":20,"source":"openstreetmap.org","min_zoom":11.0,"tier":2,"id":-1614565,"osm_relation":true}},{"geometry":{"type":"Polygon","coordinates":[[[-2.2865272,53.44880684],[-2.28628588,53.4490908],[-2.28515625,53.44903852],[-2.28515625,53.44880684],[-2.2865272,53.44880684]]]},"type":"Feature","properties":{"source":"openstreetmap.org","kind":"recreation_ground","tier":4,"area":130210,"sort_rank":57,"min_zoom":13.0,"id":59188622}},{"geometry":{"type":"Polygon","coordinates":[[[-2.28743563,53.4507851],[-2.28662751,53.4510866],[-2.2858201,53.45031931],[-2.28662823,53.4500178],[-2.28743563,53.4507851]]]},"type":"Feature","properties":{"kind":"pitch","area":17969,"sort_rank":100,"source":"openstreetmap.org","min_zoom":15.0,"tier":6,"sport":"soccer","id":323153590}},{"geometry":{"type":"Point","coordinates":[-2.28662787,53.4505522]},"type":"Feature","properties":{"label_placement":true,"kind":"pitch","area":17969,"sort_rank":100,"source":"openstreetmap.org","min_zoom":15.0,"tier":6,"sport":"soccer","id":323153590}},{"geometry":{"type":"Polygon","coordinates":[[[-2.28622381,53.45207811],[-2.28624878,53.452067],[-2.28637221,53.45203507],[-2.28653741,53.45202228],[-2.28666883,53.45203977],[-2.28674775,53.45207811],[-2.28622381,53.45207811]]]},"type":"Feature","properties":{"source":"openstreetmap.org","kind":"grass","area":6040,"sort_rank":32,"min_zoom":10.98,"id":241948026}}]}}